setup.py
cidaas_interceptor/__init__.py
cidaas_interceptor.egg-info/PKG-INFO
cidaas_interceptor.egg-info/SOURCES.txt
cidaas_interceptor.egg-info/dependency_links.txt
cidaas_interceptor.egg-info/not-zip-safe
cidaas_interceptor.egg-info/top_level.txt