Metadata-Version: 1.0
Name: cidaas-interceptor
Version: 0.3
Summary: Python cidaas interceptor
Home-page: http://github.com/cidaas/cidaasinterceptor
Author: cidaas
Author-email: cidaasmanagement@gmail.com
License: UNKNOWN
Platform: UNKNOWN
